LICENSE
MANIFEST.in
README.md
setup.py
wcxf/__init__.py
wcxf/classes.py
wcxf/cli.py
wcxf/test_bases.py
wcxf/test_cli.py
wcxf/test_smeft.py
wcxf/test_wcxf.py
wcxf/test_wet.py
wcxf.egg-info/PKG-INFO
wcxf.egg-info/SOURCES.txt
wcxf.egg-info/dependency_links.txt
wcxf.egg-info/entry_points.txt
wcxf.egg-info/requires.txt
wcxf.egg-info/top_level.txt
wcxf/bases/smeft.eft.json
wcxf/bases/smeft.warsaw.basis.json
wcxf/bases/wet-2.eft.json
wcxf/bases/wet-2.jms.basis.json
wcxf/bases/wet-3.bern.basis.json
wcxf/bases/wet-3.eft.json
wcxf/bases/wet-3.flavio.basis.json
wcxf/bases/wet-3.jms.basis.json
wcxf/bases/wet-4.bern.basis.json
wcxf/bases/wet-4.eft.json
wcxf/bases/wet-4.flavio.basis.json
wcxf/bases/wet-4.jms.basis.json
wcxf/bases/wet.bern.basis.json
wcxf/bases/wet.eft.json
wcxf/bases/wet.eos.basis.json
wcxf/bases/wet.flavio.basis.json
wcxf/bases/wet.flavorkit.basis.json
wcxf/bases/wet.formflavor.basis.json
wcxf/bases/wet.jms.basis.json
wcxf/bases/child/smeft.warsaw-mass.basis.json
wcxf/bases/child/smeft.warsaw-up.basis.json
wcxf/converters/SMEFTsim_param_card_elements.py
wcxf/converters/__init__.py
wcxf/converters/dsixtools.py
wcxf/converters/dsixtools_definitions.py
wcxf/converters/eos.py
wcxf/converters/smeftsim.py
wcxf/converters/test_dsixtools.py
wcxf/converters/test_eos.py
wcxf/converters/test_smeftsim.py
wcxf/converters/yamljson.py
wcxf/data/WCsInput-CPV-SMEFT.json
wcxf/data/WCsInput-CPV-SMEFT.yaml
wcxf/data/eos_btos.yaml
wcxf/data/eos_btou.yaml
wcxf/data/flavorkit_jms.json
wcxf/data/flavorkit_jms_conj.json
wcxf/data/test.Warsaw_mass.yml
wcxf/data/test.Warsaw_mass_incomplete.yml
wcxf/data/test.basis1.yml
wcxf/data/test.basis2.yml
wcxf/data/test.basis3.yml
wcxf/data/test.eft.yml
wcxf/data/test.otherbasis1.yml
wcxf/data/test.othereft.yml
wcxf/data/test.wcs.bern.out.yml
wcxf/data/test.wcs.bern.yml
wcxf/data/test.wcs.bern2.out.yml
wcxf/data/test.wcs.flavio.out.yml
wcxf/data/test.wcs.flavio.yml
wcxf/data/test.wcs.jms.yml
wcxf/data/test.wcs.yml
wcxf/matchers/__init__.py
wcxf/translators/__init__.py