Metadata-Version: 2.1
Name: wcxf
Version: 1.6.2
Summary: Python API and command line interface for the Wilson Coefficient exchange format
Home-page: https://wcxf.github.io
Author: David M. Straub, Jason Aebischer
Author-email: david.straub@tum.de, jason.aebischer@tum.de
License: MIT
Platform: UNKNOWN
Provides-Extra: testing
